apihub/__init__.py
apihub/common/__init__.py
apihub/common/db_session.py
apihub/common/queries.py
apihub/result.py
apihub/security/__init__.py
apihub/security/depends.py
apihub/security/helpers.py
apihub/security/models.py
apihub/security/queries.py
apihub/security/router.py
apihub/security/schemas.py
apihub/server.py
apihub/subscription/__init__.py
apihub/subscription/depends.py
apihub/subscription/helpers.py
apihub/subscription/models.py
apihub/subscription/queries.py
apihub/subscription/router.py
apihub/subscription/schemas.py
apihub/utils.py
apihub-0.1.0.dist-info/entry_points.txt
apihub-0.1.0.dist-info/LICENSE
apihub-0.1.0.dist-info/WHEEL
apihub-0.1.0.dist-info/METADATA
apihub-0.1.0.dist-info/RECORD
